py_boiler/__init__.py
py_boiler/app.py
py_boiler/templates.py
py_boiler_tools-2.0.3.dist-info/licenses/LICENSE
py_boiler_tools-2.0.3.dist-info/METADATA
py_boiler_tools-2.0.3.dist-info/WHEEL
py_boiler_tools-2.0.3.dist-info/entry_points.txt
py_boiler_tools-2.0.3.dist-info/top_level.txt
py_boiler_tools-2.0.3.dist-info/RECORD
