Metadata-Version: 2.4
Name: py_boiler_tools
Version: 2.0.3
Summary: A fast and flexible scaffolding tool for Python applications.
Author-email: Delali Funani <dfunani@gmail.com>
License:                                  Apache License
Project-URL: Homepage, https://github.com/dfunani/py_boiler
Project-URL: Repository, https://github.com/dfunani/py_boiler
Project-URL: Issues, https://github.com/dfunani/py_boiler/issues
Keywords: scaffold,boilerplate,python,starter,generator
Classifier: License :: OSI Approved :: MIT License
Classifier: Programming Language :: Python
Classifier: Programming Language :: Python :: 3
Requires-Python: >=3.10
License-File: LICENSE
Requires-Dist: click
Provides-Extra: dev
Requires-Dist: mypy; extra == "dev"
Requires-Dist: ruff; extra == "dev"
Requires-Dist: pytest; extra == "dev"
Requires-Dist: bumpver; extra == "dev"
Requires-Dist: twine; extra == "dev"
Requires-Dist: build; extra == "dev"
Requires-Dist: pytest-cov; extra == "dev"
Dynamic: license-file
